CHANGELOG.md
LICENSE
MANIFEST.in
README.md
django-roles-access.png
setup.py
django_roles_access/__init__.py
django_roles_access/admin.py
django_roles_access/apps.py
django_roles_access/decorator.py
django_roles_access/middleware.py
django_roles_access/mixin.py
django_roles_access/models.py
django_roles_access/tools.py
django_roles_access/utils.py
django_roles_access.egg-info/PKG-INFO
django_roles_access.egg-info/SOURCES.txt
django_roles_access.egg-info/dependency_links.txt
django_roles_access.egg-info/top_level.txt
django_roles_access/locale/es/LC_MESSAGES/django.mo
django_roles_access/locale/es/LC_MESSAGES/django.po
django_roles_access/management/__init__.py
django_roles_access/management/__init__.pyc
django_roles_access/management/__pycache__/__init__.cpython-35.pyc
django_roles_access/management/__pycache__/__init__.cpython-36.pyc
django_roles_access/management/__pycache__/__init__.cpython-37.pyc
django_roles_access/management/commands/__init__.py
django_roles_access/management/commands/__init__.pyc
django_roles_access/management/commands/checkviewaccess.py
django_roles_access/management/commands/checkviewaccess.pyc
django_roles_access/management/commands/__pycache__/__init__.cpython-35.pyc
django_roles_access/management/commands/__pycache__/__init__.cpython-36.pyc
django_roles_access/management/commands/__pycache__/__init__.cpython-37.pyc
django_roles_access/management/commands/__pycache__/checkviewaccess.cpython-35.pyc
django_roles_access/management/commands/__pycache__/checkviewaccess.cpython-36.pyc
django_roles_access/management/commands/__pycache__/checkviewaccess.cpython-37.pyc
django_roles_access/migrations/0001_initial.py
django_roles_access/migrations/__init__.py
django_roles_access/migrations/__pycache__/0001_initial.cpython-37.pyc
django_roles_access/migrations/__pycache__/__init__.cpython-37.pyc
django_roles_access/templatetags/__init__.py
django_roles_access/templatetags/__init__.pyc
django_roles_access/templatetags/roles_tags.py
django_roles_access/templatetags/roles_tags.pyc
django_roles_access/templatetags/__pycache__/__init__.cpython-35.pyc
django_roles_access/templatetags/__pycache__/__init__.cpython-36.pyc
